{
  "$schema": "https://developer.microsoft.com/json-schemas/fabric/item/report/definition/visualContainer/2.10.0/schema.json",
  "name": "37fcf7492bb8ec34f9cc",
  "position": {
    "x": 668,
    "y": 514,
    "z": 38000,
    "height": 266,
    "width": 346,
    "tabOrder": 38000
  },
  "visual": {
    "visualType": "scatterChart",
    "query": {
      "queryState": {
        "Category": {
          "projections": [
            {
              "field": {
                "Column": {
                  "Expression": {
                    "SourceRef": {
                      "Entity": "gold FactListings"
                    }
                  },
                  "Property": "ListingSK"
                }
              },
              "queryRef": "gold FactListings.ListingSK",
              "nativeQueryRef": "ListingSK",
              "active": true
            }
          ]
        },
        "Series": {
          "projections": [
            {
              "field": {
                "Column": {
                  "Expression": {
                    "SourceRef": {
                      "Entity": "gold DimRoom"
                    }
                  },
                  "Property": "RoomType"
                }
              },
              "queryRef": "gold DimRoom.RoomType",
              "nativeQueryRef": "RoomType"
            }
          ]
        },
        "Tooltips": {
          "projections": [
            {
              "field": {
                "Measure": {
                  "Expression": {
                    "SourceRef": {
                      "Entity": "gold FactListings"
                    }
                  },
                  "Property": "Avg Satisfaction %"
                }
              },
              "queryRef": "gold FactListings.Avg Satisfaction %",
              "nativeQueryRef": "Avg Satisfaction %"
            }
          ]
        },
        "X": {
          "projections": [
            {
              "field": {
                "Measure": {
                  "Expression": {
                    "SourceRef": {
                      "Entity": "gold FactListings"
                    }
                  },
                  "Property": "Avg Distance KM"
                }
              },
              "queryRef": "gold FactListings.Avg Distance KM",
              "nativeQueryRef": "Avg Distance KM",
              "active": true
            }
          ]
        },
        "Y": {
          "projections": [
            {
              "field": {
                "Measure": {
                  "Expression": {
                    "SourceRef": {
                      "Entity": "gold FactListings"
                    }
                  },
                  "Property": "Avg Price EUR"
                }
              },
              "queryRef": "gold FactListings.Avg Price EUR",
              "nativeQueryRef": "Avg Price EUR"
            }
          ]
        }
      },
      "sortDefinition": {
        "sort": [
          {
            "field": {
              "Measure": {
                "Expression": {
                  "SourceRef": {
                    "Entity": "gold FactListings"
                  }
                },
                "Property": "Avg Price EUR"
              }
            },
            "direction": "Descending"
          }
        ]
      }
    },
    "objects": {
      "categoryAxis": [
        {
          "properties": {
            "show": {
              "expr": {
                "Literal": {
                  "Value": "true"
                }
              }
            },
            "axisType": {
              "expr": {
                "Literal": {
                  "Value": "'Scalar'"
                }
              }
            },
            "fontFamily": {
              "expr": {
                "Literal": {
                  "Value": "'Segoe UI'"
                }
              }
            },
            "fontSize": {
              "expr": {
                "Literal": {
                  "Value": "9D"
                }
              }
            },
            "labelColor": {
              "solid": {
                "color": {
                  "expr": {
                    "Literal": {
                      "Value": "'#6B6B6B'"
                    }
                  }
                }
              }
            },
            "showAxisTitle": {
              "expr": {
                "Literal": {
                  "Value": "true"
                }
              }
            },
            "titleText": {
              "expr": {
                "Literal": {
                  "Value": "'Distance (km)'"
                }
              }
            },
            "titleFontSize": {
              "expr": {
                "Literal": {
                  "Value": "9.5D"
                }
              }
            },
            "titleColor": {
              "solid": {
                "color": {
                  "expr": {
                    "Literal": {
                      "Value": "'#6B6B6B'"
                    }
                  }
                }
              }
            },
            "gridlineShow": {
              "expr": {
                "Literal": {
                  "Value": "false"
                }
              }
            }
          }
        }
      ],
      "valueAxis": [
        {
          "properties": {
            "show": {
              "expr": {
                "Literal": {
                  "Value": "true"
                }
              }
            },
            "fontFamily": {
              "expr": {
                "Literal": {
                  "Value": "'Segoe UI'"
                }
              }
            },
            "fontSize": {
              "expr": {
                "Literal": {
                  "Value": "9D"
                }
              }
            },
            "labelColor": {
              "solid": {
                "color": {
                  "expr": {
                    "Literal": {
                      "Value": "'#6B6B6B'"
                    }
                  }
                }
              }
            },
            "showAxisTitle": {
              "expr": {
                "Literal": {
                  "Value": "true"
                }
              }
            },
            "titleText": {
              "expr": {
                "Literal": {
                  "Value": "'Avg price'"
                }
              }
            },
            "titleFontSize": {
              "expr": {
                "Literal": {
                  "Value": "9.5D"
                }
              }
            },
            "titleColor": {
              "solid": {
                "color": {
                  "expr": {
                    "Literal": {
                      "Value": "'#6B6B6B'"
                    }
                  }
                }
              }
            },
            "gridlineShow": {
              "expr": {
                "Literal": {
                  "Value": "true"
                }
              }
            },
            "gridlineColor": {
              "solid": {
                "color": {
                  "expr": {
                    "Literal": {
                      "Value": "'#E9E9E9'"
                    }
                  }
                }
              }
            },
            "gridlineThickness": {
              "expr": {
                "Literal": {
                  "Value": "1D"
                }
              }
            },
            "gridlineTransparency": {
              "expr": {
                "Literal": {
                  "Value": "0D"
                }
              }
            }
          }
        }
      ],
      "legend": [
        {
          "properties": {
            "show": {
              "expr": {
                "Literal": {
                  "Value": "true"
                }
              }
            },
            "position": {
              "expr": {
                "Literal": {
                  "Value": "'Top'"
                }
              }
            },
            "showTitle": {
              "expr": {
                "Literal": {
                  "Value": "false"
                }
              }
            },
            "fontFamily": {
              "expr": {
                "Literal": {
                  "Value": "'Segoe UI'"
                }
              }
            },
            "fontSize": {
              "expr": {
                "Literal": {
                  "Value": "10D"
                }
              }
            },
            "labelColor": {
              "solid": {
                "color": {
                  "expr": {
                    "Literal": {
                      "Value": "'#6B6B6B'"
                    }
                  }
                }
              }
            }
          }
        }
      ],
      "dataPoint": [
        {
          "properties": {
            "fill": {
              "solid": {
                "color": {
                  "expr": {
                    "Literal": {
                      "Value": "'#FF385C'"
                    }
                  }
                }
              }
            }
          },
          "selector": {
            "data": [
              {
                "scopeId": {
                  "Comparison": {
                    "ComparisonKind": 0,
                    "Left": {
                      "Column": {
                        "Expression": {
                          "SourceRef": {
                            "Entity": "gold DimRoom"
                          }
                        },
                        "Property": "RoomType"
                      }
                    },
                    "Right": {
                      "Literal": {
                        "Value": "'Entire home/apt'"
                      }
                    }
                  }
                }
              }
            ]
          }
        },
        {
          "properties": {
            "fill": {
              "solid": {
                "color": {
                  "expr": {
                    "Literal": {
                      "Value": "'#00A89D'"
                    }
                  }
                }
              }
            }
          },
          "selector": {
            "data": [
              {
                "scopeId": {
                  "Comparison": {
                    "ComparisonKind": 0,
                    "Left": {
                      "Column": {
                        "Expression": {
                          "SourceRef": {
                            "Entity": "gold DimRoom"
                          }
                        },
                        "Property": "RoomType"
                      }
                    },
                    "Right": {
                      "Literal": {
                        "Value": "'Private room'"
                      }
                    }
                  }
                }
              }
            ]
          }
        },
        {
          "properties": {
            "fill": {
              "solid": {
                "color": {
                  "expr": {
                    "Literal": {
                      "Value": "'#FC642D'"
                    }
                  }
                }
              }
            }
          },
          "selector": {
            "data": [
              {
                "scopeId": {
                  "Comparison": {
                    "ComparisonKind": 0,
                    "Left": {
                      "Column": {
                        "Expression": {
                          "SourceRef": {
                            "Entity": "gold DimRoom"
                          }
                        },
                        "Property": "RoomType"
                      }
                    },
                    "Right": {
                      "Literal": {
                        "Value": "'Shared room'"
                      }
                    }
                  }
                }
              }
            ]
          }
        }
      ],
      "trend": [
        {
          "properties": {
            "show": {
              "expr": {
                "Literal": {
                  "Value": "true"
                }
              }
            },
            "width": {
              "expr": {
                "Literal": {
                  "Value": "2D"
                }
              }
            },
            "lineColor": {
              "solid": {
                "color": {
                  "expr": {
                    "Literal": {
                      "Value": "'#8B8B8B'"
                    }
                  }
                }
              }
            },
            "transparency": {
              "expr": {
                "Literal": {
                  "Value": "25D"
                }
              }
            },
            "style": {
              "expr": {
                "Literal": {
                  "Value": "'dashed'"
                }
              }
            },
            "combineSeries": {
              "expr": {
                "Literal": {
                  "Value": "true"
                }
              }
            }
          }
        }
      ]
    },
    "visualContainerObjects": {
      "title": [
        {
          "properties": {
            "show": {
              "expr": {
                "Literal": {
                  "Value": "true"
                }
              }
            },
            "text": {
              "expr": {
                "Literal": {
                  "Value": "'Price vs Distance (≤ €1,000)'"
                }
              }
            },
            "titleWrap": {
              "expr": {
                "Literal": {
                  "Value": "true"
                }
              }
            },
            "fontFamily": {
              "expr": {
                "Literal": {
                  "Value": "'Segoe UI'"
                }
              }
            },
            "fontSize": {
              "expr": {
                "Literal": {
                  "Value": "13D"
                }
              }
            },
            "bold": {
              "expr": {
                "Literal": {
                  "Value": "true"
                }
              }
            },
            "fontColor": {
              "solid": {
                "color": {
                  "expr": {
                    "Literal": {
                      "Value": "'#222222'"
                    }
                  }
                }
              }
            },
            "alignment": {
              "expr": {
                "Literal": {
                  "Value": "'left'"
                }
              }
            }
          }
        }
      ],
      "visualHeader": [
        {
          "properties": {
            "show": {
              "expr": {
                "Literal": {
                  "Value": "false"
                }
              }
            }
          }
        }
      ],
      "background": [
        {
          "properties": {
            "show": {
              "expr": {
                "Literal": {
                  "Value": "false"
                }
              }
            }
          }
        }
      ],
      "border": [
        {
          "properties": {
            "show": {
              "expr": {
                "Literal": {
                  "Value": "false"
                }
              }
            }
          }
        }
      ],
      "padding": [
        {
          "properties": {
            "top": {
              "expr": {
                "Literal": {
                  "Value": "5D"
                }
              }
            },
            "bottom": {
              "expr": {
                "Literal": {
                  "Value": "5D"
                }
              }
            },
            "left": {
              "expr": {
                "Literal": {
                  "Value": "5D"
                }
              }
            },
            "right": {
              "expr": {
                "Literal": {
                  "Value": "5D"
                }
              }
            }
          },
          "selector": {
            "id": "default"
          }
        }
      ],
      "visualTooltip": [
        {
          "properties": {
            "show": {
              "expr": {
                "Literal": {
                  "Value": "true"
                }
              }
            },
            "type": {
              "expr": {
                "Literal": {
                  "Value": "'Default'"
                }
              }
            }
          }
        }
      ]
    },
    "drillFilterOtherVisuals": true
  },
  "filterConfig": {
    "filters": [
      {
        "name": "Filtera0c03a4fc7c0a74084669a63",
        "field": {
          "Column": {
            "Expression": {
              "SourceRef": {
                "Entity": "gold FactListings"
              }
            },
            "Property": "PriceEUR"
          }
        },
        "type": "Advanced",
        "filter": {
          "Version": 2,
          "From": [
            {
              "Name": "f",
              "Entity": "gold FactListings",
              "Type": 0
            }
          ],
          "Where": [
            {
              "Condition": {
                "Comparison": {
                  "ComparisonKind": 4,
                  "Left": {
                    "Column": {
                      "Expression": {
                        "SourceRef": {
                          "Source": "f"
                        }
                      },
                      "Property": "PriceEUR"
                    }
                  },
                  "Right": {
                    "Literal": {
                      "Value": "1000D"
                    }
                  }
                }
              }
            }
          ]
        },
        "howCreated": "User"
      }
    ]
  }
}